pyams_workflow/__init__.py
pyams_workflow/content.py
pyams_workflow/include.py
pyams_workflow/interfaces.py
pyams_workflow/versions.py
pyams_workflow/workflow.py
pyams_workflow/doctests/README.rst
pyams_workflow/locales/pyams_workflow.pot
pyams_workflow/locales/fr/LC_MESSAGES/pyams_workflow.mo
pyams_workflow/locales/fr/LC_MESSAGES/pyams_workflow.po
pyams_workflow/tests/__init__.py
pyams_workflow/tests/test_utilsdocs.py
pyams_workflow/tests/test_utilsdocstrings.py
pyams_workflow/zmi/__init__.py
pyams_workflow/zmi/history.py
pyams_workflow/zmi/transition.py
pyams_workflow/zmi/viewlet/__init__.py
pyams_workflow/zmi/viewlet/transitions.py
pyams_workflow/zmi/viewlet/versions.py
pyams_workflow-2.2.0.dist-info/LICENSE
pyams_workflow-2.2.0.dist-info/METADATA
pyams_workflow-2.2.0.dist-info/WHEEL
pyams_workflow-2.2.0.dist-info/namespace_packages.txt
pyams_workflow-2.2.0.dist-info/top_level.txt
pyams_workflow-2.2.0.dist-info/RECORD
