Metadata-Version: 2.1
Name: pyams-workflow
Version: 2.2.0
Summary: PyAMS workflow management package
Home-page: https://pyams.readthedocs.io
Author: Thierry Florac
Author-email: tflorac@ulthar.net
License: ZPL
Keywords: Pyramid PyAMS workflow
Classifier: License :: OSI Approved :: Zope Public License
Classifier: Development Status :: 4 - Beta
Classifier: Programming Language :: Python
Classifier: Framework :: Pyramid
Classifier: Topic :: Software Development :: Libraries :: Python Modules
License-File: LICENSE
Requires-Dist: setuptools
Requires-Dist: persistent
Requires-Dist: pyams-security
Requires-Dist: pyams-utils >=2.5.0
Requires-Dist: pyramid >=2.0.0
Requires-Dist: zope.annotation
Requires-Dist: zope.component
Requires-Dist: zope.componentvocabulary
Requires-Dist: zope.container
Requires-Dist: zope.dublincore
Requires-Dist: zope.interface
Requires-Dist: zope.lifecycleevent
Requires-Dist: zope.location
Requires-Dist: zope.schema
Requires-Dist: zope.traversing
Provides-Extra: test
Requires-Dist: pyams-zmi >2.1.0 ; extra == 'test'
Requires-Dist: pyramid-zcml ; extra == 'test'
Requires-Dist: zope.exceptions ; extra == 'test'
